caleb/__init__.py
caleb/__version__.py
caleb/app.py
caleb/cmdline.py
caleb/file_handler.py
caleb/reference.py
caleb-0.7.0.dist-info/entry_points.txt
caleb-0.7.0.dist-info/LICENSE
caleb-0.7.0.dist-info/WHEEL
caleb-0.7.0.dist-info/METADATA
caleb-0.7.0.dist-info/RECORD
