Metadata-Version: 2.1
Name: caleb
Version: 0.7.0
Summary: A tool to automatically retrieve bibtex entries
Home-page: https://github.com/kevinywlui/caleb
License: MIT
Keywords: latex,python,crossref
Author: kevin lui
Author-email: kevinywlui@gmail.com
Requires-Python: >=3.6,<4.0
Classifier: License :: OSI Approved :: MIT License
Classifier: Operating System :: OS Independent
Classifier: Programming Language :: Python :: 3
Classifier: Programming Language :: Python :: 3.6
Classifier: Programming Language :: Python :: 3.7
Classifier: Topic :: Text Processing :: Markup :: LaTeX
Requires-Dist: crossref-commons (>=0.0.6,<0.0.7)
Requires-Dist: mypy (>=0.720.0,<0.721.0)
Requires-Dist: requests (>=2.22,<3.0)
